yufuquantsdk/__init__.py
yufuquantsdk/_test.py
yufuquantsdk/_test2.py
yufuquantsdk/clients.py
yufuquantsdk-0.1.1.dist-info/LICENSE
yufuquantsdk-0.1.1.dist-info/WHEEL
yufuquantsdk-0.1.1.dist-info/METADATA
yufuquantsdk-0.1.1.dist-info/RECORD
