Metadata-Version: 2.1
Name: yufuquantsdk
Version: 0.1.1
Summary: SDK for yufuquant development.
Home-page: https://github.com/yufuquant/yufuquant-sdk
License: MIT
Author: zmrenwu
Author-email: zmrenwu@163.com
Requires-Python: >=3.7,<4
Classifier: License :: OSI Approved :: MIT License
Classifier: Programming Language :: Python :: 3
Classifier: Programming Language :: Python :: 3.7
Classifier: Programming Language :: Python :: 3.8
Requires-Dist: httpx (>=0.14.2,<0.15.0)
Requires-Dist: websockets (>=8.1,<9.0)
Project-URL: Repository, https://github.com/yufuquant/yufuquant-sdk
